odoo/addons/sale_coupon_free_shipping_default_product/README.rst
odoo/addons/sale_coupon_free_shipping_default_product/__init__.py
odoo/addons/sale_coupon_free_shipping_default_product/__manifest__.py
odoo/addons/sale_coupon_free_shipping_default_product/description/icon.png
odoo/addons/sale_coupon_free_shipping_default_product/description/index.html
odoo/addons/sale_coupon_free_shipping_default_product/i18n/sale_coupon_free_shipping_default_product.pot
odoo/addons/sale_coupon_free_shipping_default_product/models/__init__.py
odoo/addons/sale_coupon_free_shipping_default_product/models/coupon_program.py
odoo/addons/sale_coupon_free_shipping_default_product/models/res_company.py
odoo/addons/sale_coupon_free_shipping_default_product/models/res_config_settings.py
odoo/addons/sale_coupon_free_shipping_default_product/readme/CONTEXT.rst
odoo/addons/sale_coupon_free_shipping_default_product/readme/CONTRIBUTORS.rst
odoo/addons/sale_coupon_free_shipping_default_product/readme/DESCRIPTION.rst
odoo/addons/sale_coupon_free_shipping_default_product/readme/USAGE.rst
odoo/addons/sale_coupon_free_shipping_default_product/static/description/icon.png
odoo/addons/sale_coupon_free_shipping_default_product/static/description/index.html
odoo/addons/sale_coupon_free_shipping_default_product/tests/__init__.py
odoo/addons/sale_coupon_free_shipping_default_product/tests/test_sale_coupon_free_shipping_default_product.py
odoo/addons/sale_coupon_free_shipping_default_product/views/res_config_settings_views.xml
odoo14_addon_sale_coupon_free_shipping_default_product-14.0.1.0.1.dev2.dist-info/METADATA
odoo14_addon_sale_coupon_free_shipping_default_product-14.0.1.0.1.dev2.dist-info/WHEEL
odoo14_addon_sale_coupon_free_shipping_default_product-14.0.1.0.1.dev2.dist-info/top_level.txt
odoo14_addon_sale_coupon_free_shipping_default_product-14.0.1.0.1.dev2.dist-info/RECORD
